{
  "cases": "scripts/reminder_test_cases.json",
  "offset": 388,
  "limit": 1,
  "run_all": false,
  "batch_size": 32,
  "timeout_seconds": 120.0,
  "timezone": "Asia/Tokyo",
  "use_case_timestamps": false,
  "transport": "business-clawscale",
  "batch_id": "reminder-normal-a240ee8c02",
  "platform": "business",
  "character_id": "69eeeee7e7ef890c105124bf",
  "user_ids": [
    "3c65f19480c5d5bb87426858"
  ],
  "summary": {
    "total": 1,
    "passed": 1,
    "failed": 0,
    "pass_rate": 1.0,
    "by_error": {},
    "failures": []
  },
  "results": [
    {
      "index": 388,
      "input": "明天下午五点半我有个会议，记得提前提醒我",
      "user_id": "3c65f19480c5d5bb87426858",
      "original_from_user": "693ec8e57fad1aa21e9edbb2",
      "input_message_id": "69f234e386bb85237b3d3458",
      "input_status": "handled",
      "passed": true,
      "errors": [],
      "outputs": [
        {
          "_id": "69f234ed5f7e042740b8cc60",
          "expect_output_timestamp": 1777480941,
          "handled_timestamp": 1777480941,
          "status": "pending",
          "message_type": "text",
          "message": "请问您希望提前多久提醒您？比如提前15分钟、30分钟还是1小时？",
          "metadata": {
            "source": "clawscale",
            "batch_id": "reminder-normal-a240ee8c02",
            "case_index": 388,
            "original_from_user": "693ec8e57fad1aa21e9edbb2",
            "source_id": "693ec90a7fad1aa21e9edbb4",
            "source_eval": "reminder_normal_path_eval",
            "delivery_mode": "request_response",
            "business_protocol": {
              "delivery_mode": "request_response",
              "gateway_conversation_id": "reminder-normal-a240ee8c02-case-388",
              "business_conversation_key": "reminder-normal-a240ee8c02-case-388",
              "causal_inbound_event_id": "reminder-normal-a240ee8c02-case-388-inbound"
            }
          },
          "from_user": "69eeeee7e7ef890c105124bf",
          "platform": "business",
          "to_user": "3c65f19480c5d5bb87426858"
        }
      ],
      "reminders": [],
      "elapsed_seconds": 10.017
    }
  ]
}
